{
    "en": {
        "title": "Give Feedback",
        "subtitle": "Rate your safety briefing experience on a scale of 1-10",
        "descriptionLabel": "Description (optional)",
        "descriptionPlaceholder": "Tell us more about your experience...",
        "cancel": "Cancel",
        "submit": "Submit"
    },
    "fi": {
        "title": "Anna palautetta",
        "subtitle": "Arvioi turvallisuusperehdytyksen kokemus asteikolla 1-10",
        "descriptionLabel": "Kuvaus (valinnainen)",
        "descriptionPlaceholder": "Kerro lis채채 kokemuksestasi...",
        "cancel": "Peruuta",
        "submit": "L채het채"
    }
}